package_unique_char_counter_vl-0.0.3.dist-info/licenses/LICENSE
symbol_counter/__init__.py
symbol_counter/cli.py
symbol_counter/counter.py
package_unique_char_counter_vl-0.0.3.dist-info/METADATA
package_unique_char_counter_vl-0.0.3.dist-info/WHEEL
package_unique_char_counter_vl-0.0.3.dist-info/entry_points.txt
package_unique_char_counter_vl-0.0.3.dist-info/top_level.txt
package_unique_char_counter_vl-0.0.3.dist-info/RECORD
