Metadata-Version: 2.4
Name: package_unique_char_counter_vl
Version: 0.0.3
Summary: A package for counting unique characters in text
Author-email: Valeriia <valerialisovec606@gmail.com>
License-Expression: MIT
Classifier: Programming Language :: Python :: 3
Classifier: Operating System :: OS Independent
Requires-Python: >=3.9
License-File: LICENSE
Dynamic: license-file
